{
  "contacts": [],
  "guideStarURL": "http://www.guidestarindia.org/Summary.aspx?CCReg=10038",
  "name": "SRI SATYA SAI DHARMIKA SEVA SAMSTHA",
  "primaryEmail": "sssdvkong@gmail.com",
  "organisationType": [
    "Direct Service"
  ],
  "telephone": [
    "919246295035"
  ],
  "mainAddrress": {
    "state": "Andhra Pradesh",
    "address": [
      "D.No : 7-458, ZP Colony, Gandhi Nagar",
      "Mangamuru Road, Near YSR Statue",
      "Ongole",
      "Prakasam",
      "Andhra Pradesh",
      "523002"
    ]
  },
  "briefDescription": "Sri Satya Sai Dharmika Seva Samstha is a Registered Society which runs a Complete FREE School in the name Sri Satya Sai Samagra Vidya Kendram for the poorest of the poor. We provide FREE Education, Free Evening Nutritious Food & Time to Time Free Medical Checkups. This Academic year 284 children are getting Free Education.",
  "yearOfEstablishment": "2002"
}