{
  "contacts": [
    {
      "name": "Ishu Saini",
      "email": "JEEVANARTHFOUNDATION@GMAIL.COM",
      "designation": "Co-Founder",
      "mobile": [
        "91-9461801329"
      ]
    }
  ],
  "guideStarURL": "http://www.guidestarindia.org/Summary.aspx?CCReg=10100",
  "name": "JEEVAN ARTH FOUNDATION",
  "primaryEmail": "JEEVANARTHFOUNDATION@GMAIL.COM",
  "website": "www.jeevanarth.org",
  "organisationType": [
    "Advocacy & Campaigning",
    "Direct Service",
    "Grant-making",
    "Intermediary",
    "Network",
    "Support"
  ],
  "telephone": [
    "919461801329"
  ],
  "mainAddrress": {
    "state": "Rajasthan",
    "address": [
      "Shop No. 26, 2nd Floor,",
      "Silver Square Mall, Near Rajmandir Cinema,",
      "M.I. Road, Jaipur",
      "Jaipur",
      "Rajasthan",
      "302001"
    ]
  },
  "briefDescription": "Our NGO name is JEEVAN ARTH FOUNDATION and founder is MR. SHYAM JAIN and Co-Founder is MS. ISHU SAINI. Our dream is Safe and Strong Girls & Women's, also i want to focus on Girls Safety. Our First Program is Awareness on Females Health to Gents. and we distribution of Sanitary Napkins to whole girls & women's and also we provide certification course in NGO with pay of monthly. Our 20 member support for donation and programs. Our mission and object is want to know \"meaning of life\" and do work for life.",
  "yearOfEstablishment": "2017"
}