{
  "contacts": [],
  "guideStarURL": "http://www.guidestarindia.org/Summary.aspx?CCReg=10137",
  "name": "MOULANA AZAD SHIKSHAN SANSTHA",
  "primaryEmail": "masskap193@gmail.com",
  "organisationType": [
    "Direct Service",
    "Support"
  ],
  "telephone": [
    "919403174193"
  ],
  "mainAddrress": {
    "state": "Maharashtra",
    "address": [
      "At - Narayanpur, Post - Kapustalani Tah - Anjangaon,",
      "Amravati",
      "Maharashtra",
      "444705"
    ]
  },
  "briefDescription": "Moulana Azad Shikshan Sanstha is located in Amravati, Maharashtra.",
  "yearOfEstablishment": "2004"
}