{
  "contacts": [],
  "guideStarURL": "http://www.guidestarindia.org/Summary.aspx?CCReg=1411",
  "name": "Madurai Health and Leprosy Relief Centre",
  "primaryEmail": "humanhealthserve@rediffmail.com",
  "website": "http://www.mahelerecen.50webs.com",
  "organisationType": [
    "Direct Service",
    "Support"
  ],
  "telephone": [
    "914522360159",
    "919042484814"
  ],
  "mainAddrress": {
    "state": "Tamil Nadu",
    "address": [
      "12/10,Sister Rose 2nd Street,",
      "Melaponnagaram,",
      "Madurai",
      "Tamil Nadu",
      "625016"
    ]
  },
  "briefDescription": "Our Centre is rendering Health education, Case detection, Treatment and Rehabilitation services. Our organization is doing health education and leprosy awareness programmes to the Educational Institutions, industrial workers and also the public. Our total recorded leprosy cases are 550, and out of this cases disabled (deformity) cases are 165. We also conducting socio Economic Rehabilitation programme (SER) for the cured deformed leprosy persons to lift up their economic status. Up to now benefited persons are 60.We are interested collaborate the corporates for CSR programmes under. 1.Nutritional flour preparation by unemployed poor women. (this flour will be distributed to poor child family)2.Educational center in every slum population. appoint a one local teacher / graduate for the children.  3.Make women’s group and create the income generating activity.4.Medical camp in rural and slum areas. (dental and eye care also)5.Girl child health care.  6.Health education to all girl children age from 12 to 17 and etc.",
  "yearOfEstablishment": "1991"
}