{
  "contacts": [
    {
      "name": "Pandurang Kotre",
      "email": "bhagyaglb.2011@gmail.com",
      "designation": "SECRETARY",
      "mobile": []
    },
    {
      "name": "Milind Kotre",
      "designation": "Coordinator",
      "email": "milind.kotre@rediff.com"
    }
  ],
  "guideStarURL": "http://www.guidestarindia.org/Summary.aspx?CCReg=1576",
  "name": "Bhagya Abhivrudhi Seva Samasthe",
  "primaryEmail": "Bhagyaglb2011@gmail.com",
  "organisationType": [
    "Support"
  ],
  "telephone": [
    "919632035607"
  ],
  "mainAddrress": {
    "state": "Karnataka",
    "address": [
      "43",
      "New Venkatesh Nagar,",
      "Gulbarga",
      "Kalaburagi (Gulbarga)",
      "Karnataka",
      "585102"
    ]
  }
}