{
  "contacts": [],
  "guideStarURL": "http://www.guidestarindia.org/Summary.aspx?CCReg=1955",
  "name": "Learning Links Foundation",
  "primaryEmail": "nuriya.ansari@learninglinksindia.org",
  "website": "www.learninglinksindia.org",
  "organisationType": [
    "Direct Service",
    "Grant-making",
    "Support"
  ],
  "telephone": [
    "911140789700"
  ],
  "mainAddrress": {
    "state": "Delhi",
    "address": [
      "Allied House, 2nd Floor",
      "Block - B, Sector - 7, Vasant Kunj",
      "New Delhi",
      "Delhi",
      "110070"
    ]
  },
  "briefDescription": "Learning Links Foundation was born out of the idea that every child, youth and citizen should have an opportunity to learn and rise to their potential. We are a non-profit organisation dedicated to enhancing quality, promoting innovation and developing future ready citizens. We believe that the best possible way to achieve our goal is by delivering measurable and sustainable change in the education and innovation ecosystem.Our work in the education sector covers the entire lifecycle, from primary to higher education, including formal and non-formal segments.Our focus is to deliver solutions that address the multiple challenges around quality and learning faced by learners, service providers and Governments.Our goal is to create a future where everyone has equal opportunities by empowering students to make the most of their talent, preparing educators to transform teaching, and skilling youth to be self-reliant.",
  "yearOfEstablishment": "2002",
  "regiseredAddrress": {
    "state": "Delhi",
    "address": [
      "1209",
      "Padma Tower-I, Rajendra Place,",
      "New Delhi",
      "Delhi",
      "110008"
    ]
  }
}