{
  "contacts": [
    {
      "name": "Mary Alphonse (Dr)",
      "email": "alphonse.mary@gmail.com",
      "designation": "Principal",
      "mobile": []
    }
  ],
  "guideStarURL": "http://www.guidestarindia.org/Summary.aspx?CCReg=267",
  "name": "Nirmala Niketan Institute",
  "primaryEmail": "alphonse.mary@gmail.com",
  "organisationType": [
    "Direct Service"
  ],
  "telephone": [
    "912222035015",
    "912222067345",
    "919892253892",
    "912222014880"
  ],
  "mainAddrress": {
    "state": "Maharashtra",
    "address": [
      "Nirmala Niketan, 38 New Marin Lines",
      "Mumbai",
      "Maharashtra",
      "400020"
    ]
  },
  "regiseredAddrress": {
    "state": "Maharashtra",
    "address": [
      "Maharashtra"
    ]
  }
}