{
  "contacts": [],
  "guideStarURL": "http://www.guidestarindia.org/Summary.aspx?CCReg=3271",
  "name": "ACCEPT ( Aids Counselling Care Education and Prevention Training Society)",
  "primaryEmail": "acceptindia@gmail.com",
  "website": "www.acceptindia.org",
  "telephone": [
    "918028465802",
    "918065990452",
    "918028465802"
  ],
  "mainAddrress": {
    "state": "Karnataka",
    "address": [
      "No: 245,",
      "Krc Road, Next To Visthar,",
      "Dodda Gubbi",
      "Bengaluru (Bangalore) Urban",
      "Karnataka",
      "562149"
    ]
  }
}