{
  "contacts": [],
  "guideStarURL": "http://www.guidestarindia.org/Summary.aspx?CCReg=3318",
  "name": "Skills for Progress",
  "primaryEmail": "skip@vsnl.com",
  "website": "www.skipindia.net",
  "organisationType": [
    "Direct Service"
  ],
  "telephone": [
    "918022293814",
    "918022293814"
  ],
  "mainAddrress": {
    "state": "Karnataka",
    "address": [
      "III Floor, SKIP House, 25/1",
      "Museum Road,",
      "Bangalore",
      "Bengaluru (Bangalore) Urban",
      "Karnataka",
      "560025"
    ]
  }
}