{
  "contacts": [
    {
      "name": "Provat Kumar Mitra",
      "email": "Mitra_provat@yahoo.co.in",
      "designation": "Assistant General Secretary",
      "mobile": [
        "91-33-24300069"
      ]
    }
  ],
  "guideStarURL": "http://www.guidestarindia.org/Summary.aspx?CCReg=356",
  "name": "Economic Rural Development Society",
  "primaryEmail": "erdskol@gmail.com",
  "website": "http://www.erds.org",
  "organisationType": [
    "Direct Service"
  ],
  "telephone": [
    "913322486888",
    "913322486888"
  ],
  "mainAddrress": {
    "state": "West Bengal",
    "address": [
      "6, Kiran Sankar Roy Road",
      "Ground Floor, Room No. 3",
      "Kolkata",
      "West Bengal",
      "700001",
      "ELECTRIC BILL.doc"
    ]
  },
  "briefDescription": "ERDS came into existence in the year 1982. The urge to set up ERDS was lent by the growing poverty in villages and also in the urban areas. It is a non-profit, secular and non-political organization dedicated to ameliorate the misery and privation of the downtrodden people. It started its journey humbly in Boral, (South 24 Parganas), Vikahar, (Dakshin Dinajpur), and Thinagar, Gajole and Habibpur (Malda). ERDS has diversified its activities in various directions, women & child development, Health & Nutrition, Low Cost Sanitation, Care & rehabilitation of the elderly people, Micro-credit, Skill development training, Child trafficking, International relationship and publication. 50000 people is being served by ERDS.",
  "yearOfEstablishment": "1982"
}