{
  "contacts": [
    {
      "name": "Immanuel Bundellu",
      "email": "",
      "designation": "",
      "mobile": []
    }
  ],
  "guideStarURL": "http://www.guidestarindia.org/Summary.aspx?CCReg=4776",
  "name": "ASHA HANDICRAFTS ASSOCIATION",
  "primaryEmail": "partner@vsnl.com",
  "organisationType": [
    "Direct Service"
  ],
  "telephone": [
    "912265515353",
    "912265515353"
  ],
  "mainAddrress": {
    "state": "Maharashtra",
    "address": [
      "BEHIND SOLITAIRE HONDA SHOWROOM KASHMIRA",
      "MIRA ROAD",
      "THANE",
      "Thane",
      "Maharashtra",
      "401104"
    ]
  },
  "briefDescription": "Asha Handicrafts Association is based in Thane. Goals include Commitment to fair trade,Transparency or openness about business practices,Ethical and effective workplaces Equal employment opportunities. Concern for people and the environment Education about and advocacy of fair trade"
}