{
  "contacts": [
    {
      "name": "Ishwar Prasad",
      "email": "",
      "designation": "",
      "mobile": []
    }
  ],
  "guideStarURL": "http://www.guidestarindia.org/Summary.aspx?CCReg=6216",
  "name": "SWARAJYA BAHUUDESHIYA ASSOCIATION",
  "primaryEmail": "swarajb.aosd@yahoo.com",
  "website": "www.swarajyabahuuddeshiyaassociation.org",
  "organisationType": [
    "Advocacy & Campaigning",
    "Network",
    "Support"
  ],
  "telephone": [
    "919960213442",
    "918484090962"
  ],
  "mainAddrress": {
    "state": "Maharashtra",
    "address": [
      "Achalerkar Niwas,Nikwadi Ploting,Samta Nagar,Osmanabad",
      "Achalerkar Niwas,Nikwadi Ploting,Samta Nagar,Osmanabad, TQ.&DIST. Osmanabad.",
      "Osmanabad",
      "Maharashtra",
      "413501"
    ]
  },
  "briefDescription": "The organization was established with the object of improving live hood contestation of rural,poor people.It has vision to improve health contestation as well as education status of rural students.For this it has under taken/implemented various activities programsAbovce mentioned institute has organized an educational programme at osmanabad.In municipal shool no.11CHAIRPERSON GAVE A PRECIOUS SPEECH AND GUIDANCE TO THE STUDENTS BRIGHT FUTURE.aND THEN AFTER THE PERMISSION OF CHAIRPERSON PROGRAMME DECLARED TO BE OVER",
  "yearOfEstablishment": "4052012"
}