{
  "contacts": [
    {
      "name": "Sangitaben Dave",
      "email": "",
      "designation": "",
      "mobile": []
    }
  ],
  "guideStarURL": "http://www.guidestarindia.org/Summary.aspx?CCReg=6979",
  "name": "SHRI KALUBHAI KATARIYA MEMORIAL TRUST",
  "primaryEmail": "kk.memorialtrustdhasa@yahoo.co.in",
  "website": "www.kalubhaikatariyamemorialtrust.org",
  "organisationType": [
    "Direct Service",
    "Intermediary",
    "Support"
  ],
  "telephone": [
    "919825921557"
  ],
  "mainAddrress": {
    "state": "Gujarat",
    "address": [
      "Shri Kalubhai Katariya Marg",
      "TA. Ghadhada(SWA), Dhasa Jn",
      "Dhasa Jn, Botad",
      "Ahmedabad",
      "Gujarat",
      "364740"
    ]
  },
  "briefDescription": "We are the famous and experienced service provider. The range of services offered by us includes women development, human right, village development, environment, employment, health, agriculture, health and education and handicraft. Since 2001, our main aim is to attain the great height by helping our needy people at the best. We always believe in providing the finest and effective services.  We forever used to set our whole efforts in discovering and developing the best services to the needy. You can completely rely on our services as we always offer you the best for this",
  "yearOfEstablishment": "2001"
}