{
  "contacts": [
    {
      "name": "Piyush Roy",
      "email": "",
      "designation": "Founder",
      "mobile": []
    },
    {
      "name": "Sumit Sharma",
      "designation": "Additional Secretary",
      "email": "selfindia@hotmail.com",
      "mobile": [
        "91-9953704154"
      ]
    }
  ],
  "guideStarURL": "http://www.guidestarindia.org/Summary.aspx?CCReg=7645",
  "name": "SOCIAL EDUCATION AND LIBERTY FOUNDATION",
  "primaryEmail": "selfindia@hotmail.com",
  "website": "https://selfngodelhi.wordpress.com/",
  "organisationType": [
    "Advocacy & Campaigning",
    "Direct Service",
    "Grant-making",
    "Intermediary",
    "Network",
    "Support"
  ],
  "telephone": [
    "918586944407"
  ],
  "mainAddrress": {
    "state": "Delhi",
    "address": [
      "House No C-31  Bindapura Road Shani Bazar",
      "Nanhey Park, Nawada",
      "Uttam Nagar",
      "West Delhi",
      "Delhi",
      "110059"
    ]
  },
  "briefDescription": "The Social Education & Liberty Foundation (SELF) is alocal, non-profit and non-governmental organization.Established in 2014, SELF NGO is a national NGO with itsheadquarters in Delhi. SELF offers various fields likeeducation, health and many more which is provided tounderprivileged children, women, senior citizens, disableperson, adults and drop-out students. Our main objective is toprovide education to these people and to give equalopportunity to those people who are very weak, bothfinancially and physically. We aim to create an environmentfor holistic approach and welfare by re-energizing the potentialworkforce by enhancing skills, higher productivity andproviding gainful employment to professionals.The organization is intend",
  "yearOfEstablishment": "2014"
}