{
  "contacts": [],
  "guideStarURL": "http://www.guidestarindia.org/Summary.aspx?CCReg=9088",
  "name": "Gobardanga Haidadpur Ashar Alo Seba Samity",
  "primaryEmail": "info.asharalosebasamity@gmail.com",
  "website": "www.asharalosebasamityworld.webs.com",
  "organisationType": [
    "Direct Service"
  ],
  "telephone": [
    "918972790681"
  ],
  "mainAddrress": {
    "state": "West Bengal",
    "address": [
      "Gobardanga Haidadpur",
      "Gobardanga",
      "North 24 Parganas",
      "West Bengal",
      "743245"
    ]
  },
  "briefDescription": "Gobardanga Haidadpur Ashar Alo Seba Samity is located in Gobardanga, West Bengal.",
  "yearOfEstablishment": "2014"
}