{
  "contacts": [],
  "guideStarURL": "http://www.guidestarindia.org/Summary.aspx?CCReg=9856",
  "name": "GLOBAL RESEARCH EDUCATION AND TRAINING FOUNDATION",
  "primaryEmail": "greatfoundation@rediffmail.com",
  "website": "https://greatfoundation.org/",
  "organisationType": [
    "Direct Service",
    "Support"
  ],
  "telephone": [
    "912026832290",
    "912026832291"
  ],
  "mainAddrress": {
    "state": "Maharashtra",
    "address": [
      "B-4/21 Krishna Kewal Nagar,Opp. Rupee Co-operative Bank Kondhwa Road,",
      "Pune",
      "Maharashtra",
      "411048"
    ]
  },
  "briefDescription": "Global Research Education and Training (GREAT) Foundation is a registered trust (E/351) set up in Pune on 6 March 2002 under the Bombay Public Trust Act 1950. GREAT Foundation is working for underprivileged children with a focus on education. It believes in giving the best education, material resources and training to less privileged school children and their teachers to help them realize their full potential and become professionals."
}